LICENSE.txt
MANIFEST.in
README.rst
setup.cfg
setup.py
pyutopia.egg-info/PKG-INFO
pyutopia.egg-info/SOURCES.txt
pyutopia.egg-info/dependency_links.txt
pyutopia.egg-info/not-zip-safe
pyutopia.egg-info/requires.txt
pyutopia.egg-info/top_level.txt
tests/__init__.py
tests/test_citation.py
utopia/__init__.py
utopia/citation.py
utopia/document.py
utopia/extension.py
utopia/library.py
utopia/log.py
utopia/parser.py
utopia/serializer.py
utopia/plugins/__init__.py
utopia/tools/__init__.py