Metadata-Version: 1.1
Name: pyutopia
Version: 3.1.0.10
Summary: Utopia framework package
Home-page: https://github.com/lostislandlabs/python-utopia
Author: David Thorne
Author-email: davethorne@gmail.com
License:                     GNU GENERAL PUBLIC LICENSE
